Metadata-Version: 1.1
Name: django-filteredlist
Version: 0.1
Summary: A simple Django app to provide a generic view to filter a ListView
Home-page: https://github.com/Phil147/django-filteredlist
Author: Philipp Fahrenschon
Author-email: ph.fahrenschon@gmail.com
License: MIT License
Download-URL: https://github.com/Phil147/django-filteredlist/archive/0.1.tar.gz
Platform: UNKNOWN
Classifier: Environment :: Web Environment
Classifier: Framework :: Django
Classifier: Intended Audience :: Developers
Classifier: License :: OSI Approved :: MIT License
Classifier: Operating System :: OS Independent
Classifier: Programming Language :: Python
Classifier: Programming Language :: Python :: 3
Classifier: Topic :: Software Development :: Libraries :: Python Modules
